[{"id":"3XL","gender":"Female"},
{"id":"XL","gender":"Female"},
{"id":"S","gender":"Female"},
{"id":"XS","gender":"Male"},
{"id":"2XL","gender":"Male"},
{"id":"L","gender":"Female"},
{"id":"2XL","gender":"Female"},
{"id":"3XL","gender":"Female"},
{"id":"M","gender":"Female"},
{"id":"XL","gender":"Male"},
{"id":"L","gender":"Female"},
{"id":"XS","gender":"Female"},
{"id":"2XL","gender":"Male"},
{"id":"L","gender":"Female"},
{"id":"L","gender":"Male"},
{"id":"L","gender":"Female"},
{"id":"M","gender":"Male"},
{"id":"M","gender":"Female"},
{"id":"XS","gender":"Female"},
{"id":"2XL","gender":"Male"},
{"id":"XL","gender":"Male"},
{"id":"2XL","gender":"Male"},
{"id":"XS","gender":"Male"},
{"id":"L","gender":"Female"},
{"id":"S","gender":"Female"},
{"id":"3XL","gender":"Female"},
{"id":"XS","gender":"Male"},
{"id":"S","gender":"Female"},
{"id":"XL","gender":"Female"},
{"id":"L","gender":"Male"},
{"id":"S","gender":"Male"},
{"id":"S","gender":"Male"},
{"id":"L","gender":"Female"},
{"id":"3XL","gender":"Male"},
{"id":"M","gender":"Female"},
{"id":"S","gender":"Female"},
{"id":"2XL","gender":"Male"},
{"id":"XL","gender":"Female"},
{"id":"XS","gender":"Male"},
{"id":"M","gender":"Female"},
{"id":"S","gender":"Female"},
{"id":"XS","gender":"Male"},
{"id":"2XL","gender":"Male"},
{"id":"S","gender":"Female"},
{"id":"M","gender":"Female"},
{"id":"2XL","gender":"Female"},
{"id":"M","gender":"Male"},
{"id":"3XL","gender":"Male"},
{"id":"3XL","gender":"Male"},
{"id":"2XL","gender":"Male"}]